[
    {
        "nama": "M. Faruq Maulana",
        "nbi": "1462000247",
        "foto": "assets/kelompok/faruq.jpg",
        "link": "https://wa.me/6283833454679"
    },
    {
        "nama": "Agustinus Frinsen Farrelino Y",
        "nbi": "1462000263",
        "foto": "assets/kelompok/frinsen.png",
        "link": "https://wa.me/6281249165641"
    },
    {
        "nama": "Muhammad Adrian Ronaldy",
        "nbi": "1462000253",
        "foto": "assets/kelompok/ronal.jpg",
        "link": "https://wa.me/6282158993126"
    },
    {
        "nama": "Joshua Mario Agustinus",
        "nbi": "1462000219",
        "foto": "assets/kelompok/joshua.jpg",
        "link": "https://wa.me/6285236676788"
    },
    {
        "nama": "Dwi Sisharini Chandra",
        "nbi": "1462000229",
        "foto": "assets/kelompok/dwi.jpg",
        "link": "https://wa.me/6282334179856"
    },
    {
        "nama": "Aditya Putra Prasetya",
        "nbi": "1462000019",
        "foto": "assets/kelompok/adit.jpg",
        "link": "https://wa.me/6283105625329"
    }
]
